{
  "project_info": {
    "project_number": "695782042420",
    "project_id": "todoapp-e1251",
    "storage_bucket": "todoapp-e1251.appspot.com"
  },
  "client": [
    {
      "client_info": {
        "mobilesdk_app_id": "1:695782042420:android:dbe42255189400a37a9361",
        "android_client_info": {
          "package_name": "com.erol.kotlintodoapp"
        }
      },
      "oauth_client": [
        {
          "client_id": "695782042420-f3tpi0haa88h0ti31nl3jlpobqppc2k1.apps.googleusercontent.com",
          "client_type": 3
        }
      ],
      "api_key": [
        {
          "current_key": "AIzaSyBDPfEyxKhy3-w6l92lwyTN3CDKUFdNBqs"
        }
      ],
      "services": {
        "appinvite_service": {
          "other_platform_oauth_client": [
            {
              "client_id": "695782042420-f3tpi0haa88h0ti31nl3jlpobqppc2k1.apps.googleusercontent.com",
              "client_type": 3
            }
          ]
        }
      }
    }
  ],
  "configuration_version": "1"
}